Workbook
Name \A: #REF!
Name \b: #REF!
Name \c: #REF!
Name \d: #REF!
Name \i: #REF!
Name \p: #REF!
Name \v: #REF!
Name __?????02111383: #REF!
Name __?????02111420: #REF!
Name __?????02111833: #REF!
Name __?????02111834: #REF!
Name __?????02111862: #REF!
Name __?????02111863: #REF!
Name __?????02111864: #REF!
Name __?????02111865: #REF!
Name __?????02111866: #REF!
Name __?????02111869: #REF!
Name __?????02111870: #REF!
Name __?????02111905: #REF!
Name __?????02111906: #REF!
Name __?????02111908: #REF!
Name __?????02111945: #REF!
Name __?????02111948: #REF!
Name __?????02111949: #REF!
Name __?????02111950: #REF!
Name __?????02111961: #REF!
Name __?????02111964: #REF!
Name __?????02111966: #REF!
Name __?????02111973: #REF!
Name __?????02111974: #REF!
Name __?????02111975: #REF!
Name __?????02111976: #REF!
Name __?????02112002: #REF!
Name __?????02112014: #REF!
Name __?????02112029: #REF!
Name __?????02112030: #REF!
Name __?????02112031: #REF!
Name __??3: #REF!
Name ________az1: #REF!
Name _______az1: #REF!
Name ______ANG96: "$#REF!.$D$4:$D$7"
Name ______az1: #REF!
Name ______DAT1: "'file://Srvbidkug/DATAKUG/LPB-2002/BYMHD-0602-K.xls'#$BYMHD_SBB.$#REF!$#REF!:$#REF!$#REF!"
Name ______DAT10: "$#REF!.$J$6:$J$1249"
Name ______DAT11: "$#REF!.$K$6:$K$1249"
Name ______DAT12: "$#REF!.$L$6:$L$1249"
Name ______DAT13: "$#REF!.$M$6:$M$1249"
Name ______DAT14: "$#REF!.$N$6:$N$1249"
Name ______DAT15: "$#REF!.$O$6:$O$1249"
Name ______DAT16: "$#REF!.$P$6:$P$1249"
Name ______DAT17: "$#REF!.$Q$6:$Q$1249"
Name ______DAT18: "$#REF!.$R$6:$R$1249"
Name ______DAT19: "$#REF!.$S$6:$S$1249"
Name ______DAT2: "'file://Srvbidkug/DATAKUG/LPB-2002/BYMHD-0602-K.xls'#$BYMHD_SBB.$#REF!$#REF!:$#REF!$#REF!"
Name ______DAT20: "$#REF!.$T$6:$T$1249"
Name ______DAT21: "$#REF!.$U$6:$U$1249"
Name ______DAT22: "$#REF!.$V$6:$V$1249"
Name ______DAT23: "$#REF!.$W$6:$W$1249"
Name ______DAT24: "$#REF!.$X$6:$X$1249"
Name ______DAT25: "$#REF!.$Y$6:$Y$1249"

Sheet COVER
A1: HASIL EVALUASI AKI CAPEX PT. TELKOM TAHUN 2024
A3: USULAN PROGRAM PP | C3: :
A4: Nama Program | C4: :
A5: Jumlah LOP | C5: : | D5: 1
A6: Kapasitas | B6: VOLUME | C6: : | D6: 8
B7: SATUAN | C7: : | D7: PORT
A8: Nilai Program | B8: CAPEX | C8: : | D8: ='PARAMETER dan ASUMSI'!C5 -> 598334340
B9: BOP LAKWAS | C9: : | D9: =D8*E9 -> 0
A10: Capex / Line | D10: =D8/D6 -> 74791792
A11: Waktu Penyelesaian | B11: bulan | C11: : | D11: 1
A12: Rencana Selesai | C12: :
A13: Rencana Pemakaian Alpro (Lama kontrak / Stay of length pelanggan) | B13: tahun | C13: : | D13: 2
A14: Pemilihan Teknologi | C14: : | D14: FO
A15: Usulan pola kemitraan | D15: -
A16: Alasan keberadaan proyek | C16: :
A17: Kinerja Bisnis sampai tahun ke - 3 | B17: IRR | C17: : | D17: =AKI_check!D23 -> 0.27664953
B18: NPV | C18: : | D18: =AKI_check!D22 -> 1.4793255e+08
B19: BEP (TAHUN) | C19: : | D19: =AKI_check!D24 -> 2
B20: (Bulan) | D20: =AKI_check!D25 -> 3.8577437
B21: BCR | C21: :
B22: CAGR | C22: :
B23: Discount rate | C23: :
B24: Loss Rev/bln | C24: :
A25: KRITERIA INVESTASI UNTUK PERIODE PEMAKAIAN | C25: : | D25: =IF(AND(D19<D13,D18>0),"LAYAK","TIDAK LAYAK") -> TIDAK LAYAK
A27: Catatan penting | C27: : | D27: ODP yang dicatu merupakan ODP dari Witel Kudus TR4
B31: NAMA / NIK / JABATAN | D31: TANGGAL / TTD
A33: DIBUAT OLEH
A38: DIPERIKSA OLEH

Sheet REVENUE
B2: BREAKDOWN REVENUE PROJECTION
B10: NO | C10: STREAM PORTFOLIO | D10: PRODUCTS | E10: CUSTOMER NAME | F10: CUST GROUP | G10: DRIVERS | L10: REVENUE PER UNIT | Q10: REVENUE Rp.
G11: Tahun 1 | H11: Tahun 2 | I11: Tahun 3 | J11: Tahun 4 | K11: Tahun 5 | L11: =G11 -> Tahun 1 | M11: =H11 -> Tahun 2 | N11: =I11 -> Tahun 3 | O11: =J11 -> Tahun 4 | P11: =K11 -> Tahun 5 | Q11: =G11 -> Tahun 1 | R11: =H11 -> Tahun 2 | S11: =I11 -> Tahun 3 | T11: =J11 -> Tahun 4 | U11: =K11 -> Tahun 5
C13: Layanan Telkom
C14: Astinet Reguler 80 | G14: 12 | Q14: 84000000 | R14: =M14*H14 -> 0 | S14: =N14*I14 -> 0 | T14: =O14*J14 -> 0 | U14: =P14*K14 -> 0
C15: WMS | R15: =M15*H15 -> 0 | S15: =N15*I15 -> 0 | T15: =O15*J15 -> 0 | U15: =P15*K15 -> 0
C16: HSI 100 Mbps @40 Titik | G16: 12 | L16: 26760000 | Q16: =L16*G16 -> 321120000 | R16: =M16*H16 -> 0 | S16: =N16*I16 -> 0 | T16: =O16*J16 -> 0 | U16: =P16*K16 -> 0
R17: =M17*H17 -> 0 | S17: =N17*I17 -> 0 | T17: =O17*J17 -> 0 | U17: =P17*K17 -> 0
Q18: =L18*G18 -> 0 | R18: =M18*H18 -> 0 | S18: =N18*I18 -> 0 | T18: =O18*J18 -> 0 | U18: =P18*K18 -> 0
C19: SUB TOTAL | G19: =SUM(G14:G18) -> 24 | H19: =SUM(H14:H18) -> 0 | I19: =SUM(I14:I18) -> 0 | J19: =SUM(J14:J18) -> 0 | K19: =SUM(K14:K18) -> 0 | L19: =SUM(L14:L18) -> 26760000 | M19: =SUM(M14:M18) -> 0 | N19: =SUM(N14:N18) -> 0 | ... U19: =SUM(U14:U18) -> 0 | W19: =SUM(Q19:U19) -> 405120000
C21: Layanan Mitra
Q22: =L22*G22 -> 0 | R22: =M22*H22 -> 0 | S22: =N22*I22 -> 0 | T22: =O22*J22 -> 0 | U22: =P22*K22 -> 0
Q23: =L23*G23 -> 0 | R23: =M23*H23 -> 0 | S23: =N23*I23 -> 0 | T23: =O23*J23 -> 0 | U23: =P23*K23 -> 0
Q24: =L24*G24 -> 0 | R24: =M24*H24 -> 0 | S24: =N24*I24 -> 0 | T24: =O24*J24 -> 0 | U24: =P24*K24 -> 0
Q25: =L25*G25 -> 0 | R25: =M25*H25 -> 0 | S25: =N25*I25 -> 0 | T25: =O25*J25 -> 0 | U25: =P25*K25 -> 0
Q26: =L26*G26 -> 0 | R26: =M26*H26 -> 0 | S26: =N26*I26 -> 0 | T26: =O26*J26 -> 0 | U26: =P26*K26 -> 0
Q27: =L27*G27 -> 0 | R27: =M27*H27 -> 0 | S27: =N27*I27 -> 0 | T27: =O27*J27 -> 0 | U27: =P27*K27 -> 0
Q28: =L28*G28 -> 0 | R28: =M28*H28 -> 0 | S28: =N28*I28 -> 0 | T28: =O28*J28 -> 0 | U28: =P28*K28 -> 0
Q29: =L29*G29 -> 0 | R29: =M29*H29 -> 0 | S29: =N29*I29 -> 0 | T29: =O29*J29 -> 0 | U29: =P29*K29 -> 0
C33: SUB TOTAL | G33: =SUM(G22:G32) -> 0 | H33: =SUM(H22:H32) -> 0 | I33: =SUM(I22:I32) -> 0 | J33: =SUM(J22:J32) -> 0 | K33: =SUM(K22:K32) -> 0 | L33: =SUM(L22:L32) -> 0 | M33: =SUM(M22:M32) -> 0 | N33: =SUM(N22:N32) -> 0 | ... U33: =SUM(U22:U32) -> 0 | W33: =SUM(Q33:U33) -> 0
D35: =#REF! -> #REF!
B36: Grand Total | G36: =SUM(G33,G19) -> 24 | H36: =SUM(H33,H19) -> 0 | I36: =SUM(I33,I19) -> 0 | J36: =SUM(J33,J19) -> 0 | K36: =SUM(K33,K19) -> 0 | L36: =SUM(L33,L19) -> 26760000 | M36: =SUM(M33,M19) -> 0 | N36: =SUM(N33,N19) -> 0 | ... U36: =SUM(U33,U19) -> 0 | W36: =SUM(Q36:U36) -> 405120000
B38: ASSUMPTIONS
B40: 1 | C40: MACRO-ECONOMICS ASSUMPTIONS (DO NOT CHANGE)
F41: =G11 -> Tahun 1 | G41: =H11 -> Tahun 2 | H41: =#REF! -> #REF!
C42: Local Currency (LC) Spot Interest Rate1 | F42: 0.0625 | G42: 0.065 | H42: 0.0675
C43: USD Spot Interest Rate1 | F43: 0.005 | G43: 0.0075 | H43: 0.01
C44: USD/LC Rate | F44: 14569.663 | G44: 15066.854 | H44: 15591.296
C45: Inflation | F45: 0.033456 | G45: 0.03412512 | H45: 0.034807622
C46: Assumed Tax Rate | F46: 0.25 | G46: 0.25 | H46: 0.25

Sheet PARAMETER dan ASUMSI
B2: Parameter dan Asumsi
B3: KEGIATAN INVESTASI : HEM BGES TREG-5
B5: CAPEX | C5: 598334340
B6: Revenue | C6: 552000000
B7: Growth Revenue | C7: 0 | D7: sesuai tabel perhitungan rev
B8: Expenses/OPEX | C8: 0.12 | D8: 12% dari nilai aset berjalan (sitac/change/marketing/sewa)
B9: Ebitda Margin | D9: min 19,8%
B10: WACC | C10: 0.1149 | D10: merujuk pada Juksun 2022
B11: Depretiation | C11: =C5/3 -> 199444780 | D11: Straight Line dalam 3 tahun
B12: Minimal IRR | C12: =C10+2% -> 0.1349
B13: BHP, Marketing, BUA, SDM | C13: 0.2 | D13: dari revenue/tahun (hasil benchmark treg lain)
B16: EXPENSES
B17: TAHUN INVESTASI | C17: 0 | D17: 1 | E17: 2 | F17: 3
B18: Nilai ASSET | D18: =C5 -> 598334340 | E18: =D18-$C$11 -> 398889560 | F18: =E18-$C$11 -> 199444780
B19: O & M (include QE) | C19: =C18*C8 -> 0 | D19: =$C$8*$C$5 -> 71800121 | E19: =$C$8*$C$5 -> 71800121 | F19: =$C$8*$C$5 -> 71800121
B20: BHP, Marketing, BUA, SDM | D20: =$C$13*$C$6 -> 110400000 | E20: =$C$13*$C$6 -> 110400000 | F20: =$C$13*$C$6 -> 110400000
B22: Total Biaya Opex | D22: =SUM(D19:D21) -> 1.8220012e+08 | E22: =SUM(E19:E21) -> 1.8220012e+08 | F22: =SUM(F19:F21) -> 1.8220012e+08

Sheet AKI_check
C2: Parameter dan Asumsi
C6: ANALISA KELAYAKAN INVESTASI (AKI) - dalam Juta
C7: Tahun ke | D7: 0 | E7: =D7+1 -> 1 | F7: =E7+1 -> 2 | G7: =F7+1 -> 3
C8: Revenue | E8: ='PARAMETER dan ASUMSI'!C6 -> 552000000 | F8: =E8+(E8*'PARAMETER dan ASUMSI'!$C$7) -> 552000000 | G8: =F8+(F8*'PARAMETER dan ASUMSI'!$C$7) -> 552000000
C9: Expenses | D9: ='PARAMETER dan ASUMSI'!C19 -> 0 | E9: ='PARAMETER dan ASUMSI'!D22 -> 1.8220012e+08 | F9: ='PARAMETER dan ASUMSI'!E22 -> 1.8220012e+08 | G9: ='PARAMETER dan ASUMSI'!F22 -> 1.8220012e+08
C10: EBITDA | E10: =E8-E9 -> 3.6979988e+08 | F10: =F8-F9 -> 3.6979988e+08 | G10: =G8-G9 -> 3.6979988e+08
C11: EBITDA Margin | D11: =IFERROR(D10/D8,0) -> 0 | E11: =IFERROR(E10/E8,0) -> 0.66992732 | F11: =IFERROR(F10/F8,0) -> 0.66992732 | G11: =IFERROR(G10/G8,0) -> 0.66992732
C12: Depreciation | D12: 0 | E12: ='PARAMETER dan ASUMSI'!$C$11 -> 199444780 | F12: ='PARAMETER dan ASUMSI'!$C$11 -> 199444780 | G12: ='PARAMETER dan ASUMSI'!$C$11 -> 199444780
C13: EBIT | D13: =D10-D12 -> 0 | E13: =E10-E12 -> 1.703551e+08 | F13: =F10-F12 -> 1.703551e+08 | G13: =G10-G12 -> 1.703551e+08
C14: Taxes (30%) | D14: =IF(D13*30%<0,0,D13*30%) -> 0 | E14: =IF(E13*30%<0,0,E13*30%) -> 51106530 | F14: =IF(F13*30%<0,0,F13*30%) -> 51106530 | G14: =IF(G13*30%<0,0,G13*30%) -> 51106530
C15: (+) NOPAT (EBIT - Tax) | D15: =D13-D14 -> 0 | E15: =E13-E14 -> 1.1924857e+08 | F15: =F13-F14 -> 1.1924857e+08 | G15: =G13-G14 -> 1.1924857e+08
C16: (+) Depreciation | D16: =D12 -> 0 | E16: =E12 -> 199444780 | F16: =F12 -> 199444780 | G16: =G12 -> 199444780
C17: (-) CAPEX | D17: ='PARAMETER dan ASUMSI'!C5 -> 598334340 | E17: 0 | F17: 0 | G17: 0
C18: Net Cash flow | D18: =D15+D16-D17 -> -598334340 | E18: =E15+E16-E17 -> 3.1869335e+08 | F18: =F15+F16-F17 -> 3.1869335e+08 | G18: =G15+G16-G17 -> 3.1869335e+08
C19: Discounted Net Cash flow | D19: =D18 -> -598334340 | E19: =E18/(1+$D$21)^E7 -> 2.8081183e+08 | F19: =F18/(1+$D$21)^F7 -> 2.4743311e+08 | G19: =G18/(1+$D$21)^G7 -> 2.1802195e+08
C20: Cumulative Net Cash flow | D20: =D19 -> -598334340 | E20: =E19+D20 -> -3.1752251e+08 | F20: =F19+E20 -> -70089400 | G20: =G19+F20 -> 1.4793255e+08
C21: Minimal IRR | D21: ='PARAMETER dan ASUMSI'!C12 -> 0.1349
C22: NPV | D22: =D18+NPV(D21,E18:G18) -> 1.4793255e+08
C23: IRR | D23: =IRR(D18:G18) -> 0.27664953 | E23: =IF(D23>(D21),"Layak","Tidak Layak") -> Layak | F23: =IF(AND(E20<0,F20>=0),F7-1,0) -> 0 | G23: =IF(AND(F20<0,G20>=0),G7-1,0) -> 2
C24: Payback Period | D24: =MAX(E23:G23) -> 2 | E24: tahun | F24: =IF(F23>0,-E20/(-E20+F20)*12,0) -> 0 | G24: =IF(G23>0,-F20/(-F20+G20)*12,0) -> 3.8577437
D25: =MAX(F24:G24) -> 3.8577437 | E25: bulan
C27: Note:
